aliceum/__init__.py
aliceum-0.1.0.dev1.dist-info/METADATA
aliceum-0.1.0.dev1.dist-info/RECORD
aliceum-0.1.0.dev1.dist-info/WHEEL
aliceum-0.1.0.dev1.dist-info/top_level.txt
