Metadata-Version: 2.1
Name: aliceum
Version: 0.1.0.dev1
Summary: Alicia Connector Module
Home-page: http://github.com/
Author: askdevops
Author-email: askdevops@gmail.com
License: UNKNOWN
Keywords: pip,alicia,askdevops
Platform: UNKNOWN
Requires-Python: >=3
Requires-Dist: requests
Requires-Dist: json
